Workbook

Sheet 3. Summary
A1: Stock Analysis Summary
A2: Review Date: 2026-09-06
A3: Research mode: Internet search
A5: Ticker | B5: Company | C5: State | D5: Technical | E5: Fundamental | F5: Sentiment | G5: Overall Score | H5: Decision | I5: Previous Decision | J5: Review Date
A6: NVDA | B6: Nvidia Corp | C6: No Position | D6: ='2. Parameter Scores'!R2 -> 5.8 | E6: ='2. Parameter Scores'!S2 -> 9.2 | F6: ='2. Parameter Scores'!T2 -> 6.8 | G6: ='2. Parameter Scores'!U2 -> 7.26662 | H6: ='2. Parameter Scores'!V2 -> BUY | J6: 2026-09-06
A7: AAPL | B7: Apple Inc | C7: No Position | D7: ='2. Parameter Scores'!R3 -> 6.2 | E7: ='2. Parameter Scores'!S3 -> 6.6 | F7: ='2. Parameter Scores'!T3 -> 6.2 | G7: ='2. Parameter Scores'!U3 -> 6.33332 | H7: ='2. Parameter Scores'!V3 -> HOLD | J7: 2026-09-06
A8: GOOGL | B8: Alphabet Inc Class A | C8: No Position | D8: ='2. Parameter Scores'!R4 -> 4.8 | E8: ='2. Parameter Scores'!S4 -> 9 | F8: ='2. Parameter Scores'!T4 -> 8.2 | G8: ='2. Parameter Scores'!U4 -> 7.33342 | H8: ='2. Parameter Scores'!V4 -> BUY | J8: 2026-09-06
A9: MSFT | B9: Microsoft Corp | C9: No Position | D9: ='2. Parameter Scores'!R5 -> 6.8 | E9: ='2. Parameter Scores'!S5 -> 8.6 | F9: ='2. Parameter Scores'!T5 -> 6.8 | G9: ='2. Parameter Scores'!U5 -> 7.39994 | H9: ='2. Parameter Scores'!V5 -> BUY | J9: 2026-09-06
A10: AMZN | B10: Amazon.com Inc | C10: No Position | D10: ='2. Parameter Scores'!R6 -> 5.6 | E10: ='2. Parameter Scores'!S6 -> 7.6 | F10: ='2. Parameter Scores'!T6 -> 7.6 | G10: ='2. Parameter Scores'!U6 -> 6.9334 | H10: ='2. Parameter Scores'!V6 -> HOLD | J10: 2026-09-06
A11: TSM | B11: Taiwan Semiconductor Mfg (ADR) | C11: No Position | D11: ='2. Parameter Scores'!R7 -> 5 | E11: ='2. Parameter Scores'!S7 -> 9.2 | F11: ='2. Parameter Scores'!T7 -> 8.4 | G11: ='2. Parameter Scores'!U7 -> 7.53342 | H11: ='2. Parameter Scores'!V7 -> BUY | J11: 2026-09-06
A12: SPCX | B12: Space Exploration Technologies Cl A | C12: No Position | D12: ='2. Parameter Scores'!R8 -> 5.6666667 | E12: ='2. Parameter Scores'!S8 -> N/A | F12: ='2. Parameter Scores'!T8 -> 4.8 | G12: ='2. Parameter Scores'!U8 -> N/A | H12: ='2. Parameter Scores'!V8 -> NO ACTION | J12: 2026-09-06
A13: AVGO | B13: Broadcom Inc | C13: No Position | D13: ='2. Parameter Scores'!R9 -> 4.6 | E13: ='2. Parameter Scores'!S9 -> 8 | F13: ='2. Parameter Scores'!T9 -> 7.2 | G13: ='2. Parameter Scores'!U9 -> 6.60006 | H13: ='2. Parameter Scores'!V9 -> HOLD | J13: 2026-09-06
A14: META | B14: Meta Platforms Inc | C14: No Position | D14: ='2. Parameter Scores'!R10 -> 5.8 | E14: ='2. Parameter Scores'!S10 -> 7 | F14: ='2. Parameter Scores'!T10 -> 6.8 | G14: ='2. Parameter Scores'!U10 -> 6.53336 | H14: ='2. Parameter Scores'!V10 -> HOLD | J14: 2026-09-06
A15: TSLA | B15: Tesla Inc | C15: No Position | D15: ='2. Parameter Scores'!R11 -> 4.6 | E15: ='2. Parameter Scores'!S11 -> 4.4 | F15: ='2. Parameter Scores'!T11 -> 5.6 | G15: ='2. Parameter Scores'!U11 -> 4.86674 | H15: ='2. Parameter Scores'!V11 -> HOLD | J15: 2026-09-06
A18: Notes:
A19: - SPCX (SpaceX) is privately held / not a traditional publicly-traded equity as of this framework's creation; Agents 2-4 should verify current tradability status and flag heavily-null categories accordingly rather than fabricating market data.
A20: - Weights and thresholds are configurable here without touching any agent's logic.
A21: - All research agents must cite a source (URL/provider + access date, or filing reference) per parameter value; null values must include a one-line reason.

Sheet 1. Actual Values
A1: Ticker | B1: Company | C1: State | D1: Price vs 50-day MA | E1: Price vs 200-day MA | F1: RSI (14-day) | G1: Relative performance vs S&P 500 (3-month) | H1: Volatility / Beta | I1: P/E ratio vs sector average | J1: Revenue growth (YoY, most recent quarter or TTM) | K1: Earnings growth (YoY) | L1: Profit margin (operating margin, most recent) | M1: Debt-to-equity ratio | N1: Analyst consensus rating | O1: Recent analyst rating changes (last 30 days) | P1: Recent news sentiment (last 30 days) | Q1: Short interest (% of float) | R1: Insider buying/selling activity (last 90 days) | S1: Sources | T1: Review Date | U1: Previous Decision
A2: NVDA | B2: Nvidia Corp | C2: No Position | D2: +2.8% ($230.36 vs $224.03) | E2: +6.3% ($230.36 vs $216.67) | F2: 58.3 | G2: NVDA +19.6% vs S&P 500 ~+1-2% -> outperformance ~18-20pp | H2: 2.22 | I2: Trailing P/E 29.13 vs sector avg ~30-35 (roughly in-line to slightly below) | J2: TTM revenue growth +83.4% YoY | K2: TTM EPS growth +125.3% YoY | L2: Operating margin 65.2% | M2: D/E 0.17 | N2: Strong Buy - 60 analysts: 48 Strong Buy, 9 Buy, 2 Hold, 1 Strong Sell; avg PT $325.99 (+41.5% upside) | O2: Minor shift in Aug 2026, broadly no material net downgrades | P2: Mixed-to-positive: early-Aug AI sell-off, Jensen Huang urged buying the discount, Morgan Stanley bullish ahead of earnings | Q2: 1.23% of float | R2: Notable net insider selling: ~$3.3B in executive stock sales reported | S2: Investing.com Technical Analysis, accessed 2026-09-06; Kresmion Research, TECHi, accessed 2026-09-06; StockAnalysis.com, accessed 2026-09-06; StockAnalysis.com; FRED S&P 500, accessed 2026-09-06; The Motley Fool, itiger.com, accessed 2026-09-06; fintel.io/ss/us/nvda, accessed 2026-09-06; stockanalysis.com/stocks/nvda/financials, accessed 2026-09-06; stockanalysis.com/stocks/nvda/forecast, accessed 2026-09-06; stockanalysis.com/stocks/nvda/statistics, accessed 2026-09-06 | T2: 2026-09-06
A3: AAPL | B3: Apple Inc | C3: No Position | D3: -0.3% ($319.97 vs $321.06) | E3: +1.8% ($319.97 vs $314.37) | F3: 41.96 | G3: AAPL +12.8% vs S&P 500 ~+1-2% -> outperform ~11pp | H3: 1.09 | I3: Trailing P/E 36.71 vs sector avg ~30 (roughly 20% above) | J3: TTM revenue growth +14.2% YoY | K3: TTM EPS growth +32.6% YoY | L3: Operating margin 33.2% | M3: D/E 0.78 | N3: Buy - 44 analysts: 19 Strong Buy, 6 Buy, 13 Hold, 3 Sell, 3 Strong Sell; avg PT $324.53 (+1.4% upside) | O3: Net negative drift: Strong Buy fell 25->19; Sell/Strong Sell rose; UBS reaffirmed Neutral $280 | P3: Mixed: rising into Sept 9 foldable iPhone event/CEO speculation, but some flag weak sentiment into earnings | Q3: 0.80% of float | R3: Routine insider selling (10b5-1 plans), no notable buying | S3: GuruFocus, StockTitan, accessed 2026-09-06; Investing.com Technical Analysis, accessed 2026-09-06; Invezz, TipRanks, SeekingAlpha, accessed 2026-09-06; StockAnalysis.com, accessed 2026-09-06; StockAnalysis.com; FRED S&P 500, accessed 2026-09-06; fintel.io/ss/us/aapl, accessed 2026-09-06; stockanalysis.com/stocks/aapl/financials, accessed 2026-09-06; stockanalysis.com/stocks/aapl/forecast, accessed 2026-09-06; stockanalysis.com/stocks/aapl/statistics, accessed 2026-09-06; stockanalysis.com; Yahoo Finance, accessed 2026-09-06; stockanalysis.com; gurufocus.com, accessed 2026-09-06 | T3: 2026-09-06
A4: GOOGL | B4: Alphabet Inc Class A | C4: No Position | D4: -0.46% ($338.46 vs $340.02) | E4: -2.5% ($338.46 vs $347.20) | F4: 45.5 | G4: GOOGL +0.3% vs S&P 500 ~+1-2% -> roughly in line | H4: 1.22 | I4: Trailing P/E 16.98 vs sector avg ~30 (40%+ below, profitable) | J4: TTM revenue growth +20.1% YoY | K4: TTM EPS growth +112.5% YoY | L4: Operating margin 33.1% | M4: D/E 0.19 | N4: Strong Buy - 64 analysts: 46 Strong Buy, 13 Buy, 5 Hold; avg PT $428.07 (+26.5% upside) | O4: Continued bullish reiterations from Rosenblatt, Morgan Stanley; no significant downgrades | P4: Positive: Gemini 3.8 launch, antitrust court win, renewed AI momentum | Q4: 1.35% of float | R4: Routine/mixed insider selling, no notable buying, no scandal | S4: CNBC, ad-hoc-news.de, accessed 2026-09-06; Investing.com Technical Analysis, accessed 2026-09-06; MarketBeat, GuruFocus, accessed 2026-09-06; StockAnalysis.com, accessed 2026-09-06; StockAnalysis.com; FRED S&P 500, accessed 2026-09-06; fintel.io/ss/us/googl, accessed 2026-09-06; stockanalysis.com/stocks/googl/financials, accessed 2026-09-06; stockanalysis.com/stocks/googl/forecast, accessed 2026-09-06; stockanalysis.com/stocks/googl/statistics, accessed 2026-09-06 | T4: 2026-09-06
A5: MSFT | B5: Microsoft Corp | C5: No Position | D5: -1.1% ($499.70 vs $505.31) | E5: +2.4% ($499.70 vs $487.87) | F5: 42.7 | G5: MSFT +34.0% vs S&P 500 ~+1-2% -> outperform >15pp | H5: 1.11 | I5: Trailing P/E 27.84 vs sector avg ~30 (within +/-20%) | J5: FY2026 revenue growth +17.8% YoY | K5: FY2026 net income growth ~+31.3% YoY | L5: Operating margin 46.8% | M5: D/E 0.29 | N5: Strong Buy - 55 analysts: 38 Strong Buy, 14 Buy, 3 Hold; avg PT $571.38 (+14.3% upside) | O5: Slight bearish drift, Strong Buy 43->38, still net bullish | P5: Mixed: strong AI/Azure growth but stock sliding on capex concerns | Q5: 0.92% of float | R5: Significant net insider selling: CEO Nadella sold $43.4M in stock | S5: Benzinga, Pluang, accessed 2026-09-06; Foreign Policy Journal, ad-hoc-news.de, accessed 2026-09-06; Investing.com Technical Analysis, accessed 2026-09-06; StockAnalysis.com, accessed 2026-09-06; StockAnalysis.com; FRED S&P 500, accessed 2026-09-06; fintel.io/ss/us/msft, accessed 2026-09-06; stockanalysis.com/stocks/msft/financials, accessed 2026-09-06; stockanalysis.com/stocks/msft/forecast, accessed 2026-09-06; stockanalysis.com/stocks/msft/statistics, accessed 2026-09-06 | T5: 2026-09-06
A6: AMZN | B6: Amazon.com Inc | C6: No Position | D6: +0.14% ($258.51 vs $258.16) | E6: -1.5% ($258.51 vs $262.40) | F6: 54.6 | G6: AMZN +11.1% vs S&P 500 ~+1-2% -> outperform ~9-10pp | H6: 1.44 | I6: Trailing P/E 20.79 vs sector avg ~30 (roughly 30% below) | J6: TTM revenue growth +15.8% YoY | K6: TTM EPS/net income growth +89.7% YoY | L6: Operating margin 12.1% | M6: D/E 0.46 | N6: Strong Buy - 61 analysts: 44 Strong Buy, 15 Buy, 2 Hold; avg PT $328.17 (+27.0% upside) | O6: Stable to slightly softer, still strongly bullish | P6: Positive: AWS surge, eyeing $3T valuation on AI/AWS growth | Q6: 0.95% of float | R6: Notable net insider selling: CEO Jassy sold shares multiple times, ~$15M+ total insider dumps | S6: Investing.com Technical Analysis, accessed 2026-09-06; Investing.com, MarketScreener, Yahoo Finance, accessed 2026-09-06; StockAnalysis.com, accessed 2026-09-06; StockAnalysis.com; FRED S&P 500, accessed 2026-09-06; TradingPedia, Yahoo Finance, accessed 2026-09-06; fintel.io/ss/us/amzn, accessed 2026-09-06; stockanalysis.com/stocks/amzn/financials, accessed 2026-09-06; stockanalysis.com/stocks/amzn/forecast, accessed 2026-09-06; stockanalysis.com/stocks/amzn/statistics, accessed 2026-09-06 | T6: 2026-09-06
A7: TSM | B7: Taiwan Semiconductor Mfg (ADR) | C7: No Position | D7: +2.3% ($428.91 vs $419.10) | E7: +3.1% ($428.91 vs $416.15) | F7: 70.9 | G7: TSM -0.8% vs S&P 500 ~+1-2% -> slight underperform | H7: 1.26 | I7: Trailing P/E 28.35 vs sector avg ~30-35 (roughly in-line to slightly below) | J7: Q2 2026 revenue growth +36.1% YoY | K7: Q2 2026 EPS growth +77.4% YoY | L7: Operating margin 56.1% | M7: D/E 0.17 | N7: Strong Buy - 19 analysts: 12 Strong Buy, 6 Buy, 1 Hold; avg PT $554.45 (+29.3% upside) | O7: Positive: Stifel initiated Buy, BofA maintained Buy, strong analyst sentiment | P7: Positive: strong AI demand driving 2026 capex, some geopolitical risk headlines | Q7: 0.62% of float (declining trend) | R7: Notable net insider buying: multiple SVP/VP acquisitions reported | S7: Benzinga short interest data, accessed 2026-09-06; Investing.com Technical Analysis, accessed 2026-09-06; StockAnalysis.com, accessed 2026-09-06; StockAnalysis.com; FRED S&P 500, accessed 2026-09-06; StockTitan SEC Form 4 filings, accessed 2026-09-06; Yahoo Finance, Benzinga, accessed 2026-09-06; stockanalysis.com/stocks/tsm/financials, accessed 2026-09-06; stockanalysis.com/stocks/tsm/forecast, accessed 2026-09-06; stockanalysis.com/stocks/tsm/statistics, accessed 2026-09-06; stockanalysis.com; Yahoo Finance, accessed 2026-09-06 | T7: 2026-09-06
A8: SPCX | B8: Space Exploration Technologies Cl A | C8: No Position | D8: +3.0% ($147.95 vs $143.69) | E8: N/A | F8: 56.7 | G8: SPCX -3.4% vs S&P 500 ~+1-2% -> underperform, within -5% band | H8: N/A | I8: N/A | J8: N/A | K8: N/A | L8: N/A | M8: N/A | N8: Moderate Buy/Buy - mixed reports; MarketBeat: 2 Strong Buy/25 Buy/8 Hold/7 Sell across 42 reports; stockanalysis.com: 8 analysts all Buy, avg target ~$244 | O8: Positive price-target raises: Oppenheimer $250->$280, Bernstein $239->$248 | P8: Mixed/volatile: heavy short-seller battle, Musk warned shorts, stock rebounded ~40% off low; MarketBeat sentiment score below sector avg | Q8: Conflicting reports: MarketBeat ~1.41%, but S3 Partners/Yahoo Finance cite 32-45% of float shorted amid a ~$25B short bet post-IPO | R8: MarketBeat: no open-market insider trades in 3 months; Form 4s show large IPO-related preferred-to-common conversions for Musk plus one ~$1.2M open-market sale | S8: CNBC, Invezz, MarketBeat, accessed 2026-09-06; Investing.com Technical Analysis, accessed 2026-09-06; Investing.com Technical Analysis, accessed 2026-09-06 -- insufficient trading history for a genuine 200-day MA; MarketBeat; StockTitan Form 4, accessed 2026-09-06; S3 Partners via CNBC/Yahoo Finance, Invezz, MarketBeat, accessed 2026-09-06 -- wide variance across sources; StockAnalysis.com, accessed 2026-09-06 -- beta not yet available; StockAnalysis.com; FRED S&P 500, accessed 2026-09-06; marketbeat.com; stockanalysis.com/stocks/spcx/ratings, accessed 2026-09-06; stockanalysis.com/stocks/spcx/ratings, accessed 2026-09-06 | T8: 2026-09-06
A9: AVGO | B9: Broadcom Inc | C9: No Position | D9: -1.8% ($357.90 vs $364.45) | E9: -7.1% ($357.90 vs $385.43) | F9: 47.2 | G9: AVGO -1.95% vs S&P 500 ~+1-2% -> underperform, within -5% band | H9: 1.46 | I9: Trailing P/E 45.68 vs sector avg ~30-35 (roughly 30-50% above) | J9: Q3 2026 revenue growth +85.5% YoY | K9: Q3 2026 EPS growth +215.3% YoY | L9: Operating margin 48.6% | M9: D/E 0.60 | N9: Strong Buy - 49 analysts: 37 Strong Buy, 8 Buy, 4 Hold; avg PT $533.41 (+49.0% upside) | O9: Positive price-target raises: Citi, Cantor Fitzgerald, Raymond James all raised targets, maintaining Buy | P9: Mixed: stock down ~19% since Q4 2025 results per one report, but bullish long-term AI-chip narrative persists | Q9: 1.20% of float | R9: Significant net insider selling: CEO Hock Tan sold $42.3M worth of shares | S9: Investing.com Technical Analysis, accessed 2026-09-06; StockAnalysis.com, accessed 2026-09-06; StockAnalysis.com; FRED S&P 500, accessed 2026-09-06; Yahoo Finance, CNBC, accessed 2026-09-06; fintel.io/ss/us/avgo, accessed 2026-09-06; iTiger, TheStreet, Yahoo Finance, accessed 2026-09-06; stockanalysis.com/stocks/avgo/financials, accessed 2026-09-06; stockanalysis.com/stocks/avgo/forecast, accessed 2026-09-06; stockanalysis.com/stocks/avgo/statistics, accessed 2026-09-06 | T9: 2026-09-06
A10: META | B10: Meta Platforms Inc | C10: No Position | D10: +4.9% ($616.77 vs $588.21) | E10: +6.7% ($616.77 vs $577.83) | F10: 67 | G10: META +12.1% vs S&P 500 ~+1-2% -> outperform ~10-11pp | H10: 1.24 | I10: Trailing P/E 23.24 vs sector avg ~30 (roughly 20-25% below) | J10: Q2 2026 revenue growth +28.0% YoY | K10: Q2 2026 net income/EPS declined -13.4% YoY | L10: Operating margin 38.1% | M10: D/E 0.43 | N10: Strong Buy - 62 analysts: 47 Strong Buy, 8 Buy, 7 Hold; avg PT $754.77 (+22.4% upside) | O10: Stable, mostly reiterations from BofA, Goldman Sachs, Wedbush | P10: Mixed: pressured by high AI capex concerns, some bullish catalysts noted | Q10: 1.27% of float | R10: Notable net insider selling: ~$48M of shares sold suggesting hesitancy | S10: Investing.com Technical Analysis, accessed 2026-09-06; Morningstar, Fortune, 247wallst.com, accessed 2026-09-06; StockAnalysis.com, accessed 2026-09-06; StockAnalysis.com; FRED S&P 500, accessed 2026-09-06; Yahoo Finance (Simply Wall St), StockTitan, accessed 2026-09-06; fintel.io/ss/us/meta, accessed 2026-09-06; stockanalysis.com/stocks/meta/financials, accessed 2026-09-06; stockanalysis.com/stocks/meta/forecast, accessed 2026-09-06; stockanalysis.com/stocks/meta/statistics, accessed 2026-09-06 | T10: 2026-09-06
A11: TSLA | B11: Tesla Inc | C11: No Position | D11: -1.25% ($354.08 vs $358.55) | E11: +4.6% ($354.08 vs $338.58) | F11: 42.1 | G11: TSLA -6.75% vs S&P 500 ~+1-2% -> underperform ~8pp | H11: 1.84 | I11: Trailing P/E 367.43 vs sector avg ~20-30 (far more than 50% above) | J11: Q2 2026 revenue growth +25.5% YoY | K11: Q2 2026 net income declined -3.0% YoY | L11: Operating margin 4.13% | M11: D/E 0.18 | N11: Buy - 46 analysts: 16 Strong Buy, 6 Buy, 19 Hold, 2 Sell, 3 Strong Sell; avg PT $390.09 (+10.2% upside) | O11: Slight net negative drift, mixed recent calls (JPMorgan Hold, RBC Buy, GLJ Sell) | P11: Mixed: strong Q3 delivery expectations vs Musk pay-package controversy and Cybertruck litigation | Q11: 2.29% of float | R11: Notable net insider selling: reports of ~$300M in planned sales | S11: Investing.com Technical Analysis, accessed 2026-09-06; StockAnalysis.com, accessed 2026-09-06; StockAnalysis.com; FRED S&P 500, accessed 2026-09-06; TipRanks, accessed 2026-09-06; Yahoo Finance, Gulf News, Quartz, accessed 2026-09-06; fintel.io/ss/us/tsla, accessed 2026-09-06; stockanalysis.com/stocks/tsla/financials, accessed 2026-09-06; stockanalysis.com/stocks/tsla/forecast, accessed 2026-09-06; stockanalysis.com/stocks/tsla/statistics, accessed 2026-09-06 | T11: 2026-09-06

Sheet 2. Parameter Scores
A1: Ticker | B1: Company | C1: Price vs 50-day MA | D1: Price vs 200-day MA | E1: RSI (14-day) | F1: Relative performance vs S&P 500 (3-month) | G1: Volatility / Beta | H1: P/E ratio vs sector average | I1: Revenue growth (YoY, most recent quarter or TTM) | J1: Earnings growth (YoY) | K1: Profit margin (operating margin, most recent) | L1: Debt-to-equity ratio | M1: Analyst consensus rating | N1: Recent analyst rating changes (last 30 days) | O1: Recent news sentiment (last 30 days) | P1: Short interest (% of float) | Q1: Insider buying/selling activity (last 90 days) | R1: Technical Score | S1: Fundamental Score | T1: Sentiment Score | U1: Overall Score | V1: Decision | W1: Review Date | X1: Previous Decision
A2: NVDA | B2: Nvidia Corp | C2: 6 | D2: 7 | E2: 4 | F2: 9 | G2: 3 | H2: 6 | I2: 10 | J2: 10 | K2: 10 | L2: 10 | M2: 10 | N2: 6 | O2: 6 | P2: 10 | Q2: 2 | R2: =IFERROR(AVERAGE(C2:G2),"N/A") -> 5.8 | S2: =IFERROR(AVERAGE(H2:L2),"N/A") -> 9.2 | T2: =IFERROR(AVERAGE(M2:Q2),"N/A") -> 6.8 | U2: =IF(ISNUMBER(S2),(R2*0.3333+S2*0.3333+T2*0.3334),"N/A") -> 7.26662 | V2: =IF(NOT(ISNUMBER(U2)),"NO ACTION",IF(U2>=7,"BUY",IF(U2>=4,"HOLD","SELL"))) -> BUY | W2: 2026-09-06
A3: AAPL | B3: Apple Inc | C3: 5 | D3: 5 | E3: 6 | F3: 7 | G3: 8 | H3: 4 | I3: 7 | J3: 9 | K3: 7 | L3: 6 | M3: 8 | N3: 4 | O3: 5 | P3: 10 | Q3: 4 | R3: =IFERROR(AVERAGE(C3:G3),"N/A") -> 6.2 | S3: =IFERROR(AVERAGE(H3:L3),"N/A") -> 6.6 | T3: =IFERROR(AVERAGE(M3:Q3),"N/A") -> 6.2 | U3: =IF(ISNUMBER(S3),(R3*0.3333+S3*0.3333+T3*0.3334),"N/A") -> 6.33332 | V3: =IF(NOT(ISNUMBER(U3)),"NO ACTION",IF(U3>=7,"BUY",IF(U3>=4,"HOLD","SELL"))) -> HOLD | W3: 2026-09-06
A4: GOOGL | B4: Alphabet Inc Class A | C4: 5 | D4: 4 | E4: 5 | F4: 5 | G4: 5 | H4: 10 | I4: 8 | J4: 10 | K4: 7 | L4: 10 | M4: 10 | N4: 7 | O4: 9 | P4: 10 | Q4: 5 | R4: =IFERROR(AVERAGE(C4:G4),"N/A") -> 4.8 | S4: =IFERROR(AVERAGE(H4:L4),"N/A") -> 9 | T4: =IFERROR(AVERAGE(M4:Q4),"N/A") -> 8.2 | U4: =IF(ISNUMBER(S4),(R4*0.3333+S4*0.3333+T4*0.3334),"N/A") -> 7.33342 | V4: =IF(NOT(ISNUMBER(U4)),"NO ACTION",IF(U4>=7,"BUY",IF(U4>=4,"HOLD","SELL"))) -> BUY | W4: 2026-09-06
A5: MSFT | B5: Microsoft Corp | C5: 5 | D5: 6 | E5: 6 | F5: 9 | G5: 8 | H5: 6 | I5: 8 | J5: 9 | K5: 10 | L5: 10 | M5: 10 | N5: 6 | O5: 5 | P5: 10 | Q5: 3 | R5: =IFERROR(AVERAGE(C5:G5),"N/A") -> 6.8 | S5: =IFERROR(AVERAGE(H5:L5),"N/A") -> 8.6 | T5: =IFERROR(AVERAGE(M5:Q5),"N/A") -> 6.8 | U5: =IF(ISNUMBER(S5),(R5*0.3333+S5*0.3333+T5*0.3334),"N/A") -> 7.39994 | V5: =IF(NOT(ISNUMBER(U5)),"NO ACTION",IF(U5>=7,"BUY",IF(U5>=4,"HOLD","SELL"))) -> BUY | W5: 2026-09-06
A6: AMZN | B6: Amazon.com Inc | C6: 6 | D6: 5 | E6: 5 | F6: 7 | G6: 5 | H6: 8 | I6: 8 | J6: 10 | K6: 5 | L6: 7 | M6: 10 | N6: 7 | O6: 8 | P6: 10 | Q6: 3 | R6: =IFERROR(AVERAGE(C6:G6),"N/A") -> 5.6 | S6: =IFERROR(AVERAGE(H6:L6),"N/A") -> 7.6 | T6: =IFERROR(AVERAGE(M6:Q6),"N/A") -> 7.6 | U6: =IF(ISNUMBER(S6),(R6*0.3333+S6*0.3333+T6*0.3334),"N/A") -> 6.9334 | V6: =IF(NOT(ISNUMBER(U6)),"NO ACTION",IF(U6>=7,"BUY",IF(U6>=4,"HOLD","SELL"))) -> HOLD | W6: 2026-09-06
A7: TSM | B7: Taiwan Semiconductor Mfg (ADR) | C7: 7 | D7: 6 | E7: 2 | F7: 5 | G7: 5 | H7: 6 | I7: 10 | J7: 10 | K7: 10 | L7: 10 | M7: 10 | N7: 8 | O7: 7 | P7: 10 | Q7: 7 | R7: =IFERROR(AVERAGE(C7:G7),"N/A") -> 5 | S7: =IFERROR(AVERAGE(H7:L7),"N/A") -> 9.2 | T7: =IFERROR(AVERAGE(M7:Q7),"N/A") -> 8.4 | U7: =IF(ISNUMBER(S7),(R7*0.3333+S7*0.3333+T7*0.3334),"N/A") -> 7.53342 | V7: =IF(NOT(ISNUMBER(U7)),"NO ACTION",IF(U7>=7,"BUY",IF(U7>=4,"HOLD","SELL"))) -> BUY | W7: 2026-09-06
A8: SPCX | B8: Space Exploration Technologies Cl A | C8: 7 | E8: 5 | F8: 5 | M8: 6 | N8: 7 | O8: 5 | P8: 1 | Q8: 5 | R8: =IFERROR(AVERAGE(C8:G8),"N/A") -> 5.6666667 | S8: =IFERROR(AVERAGE(H8:L8),"N/A") -> N/A | T8: =IFERROR(AVERAGE(M8:Q8),"N/A") -> 4.8 | U8: =IF(ISNUMBER(S8),(R8*0.3333+S8*0.3333+T8*0.3334),"N/A") -> N/A | V8: NO ACTION | W8: 2026-09-06
A9: AVGO | B9: Broadcom Inc | C9: 5 | D9: 3 | E9: 5 | F9: 5 | G9: 5 | H9: 3 | I9: 10 | J9: 10 | K9: 10 | L9: 7 | M9: 10 | N9: 8 | O9: 5 | P9: 10 | Q9: 3 | R9: =IFERROR(AVERAGE(C9:G9),"N/A") -> 4.6 | S9: =IFERROR(AVERAGE(H9:L9),"N/A") -> 8 | T9: =IFERROR(AVERAGE(M9:Q9),"N/A") -> 7.2 | U9: =IF(ISNUMBER(S9),(R9*0.3333+S9*0.3333+T9*0.3334),"N/A") -> 6.60006 | V9: =IF(NOT(ISNUMBER(U9)),"NO ACTION",IF(U9>=7,"BUY",IF(U9>=4,"HOLD","SELL"))) -> HOLD | W9: 2026-09-06
A10: META | B10: Meta Platforms Inc | C10: 7 | D10: 7 | E10: 3 | F10: 7 | G10: 5 | H10: 8 | I10: 9 | J10: 1 | K10: 10 | L10: 7 | M10: 10 | N10: 6 | O10: 5 | P10: 10 | Q10: 3 | R10: =IFERROR(AVERAGE(C10:G10),"N/A") -> 5.8 | S10: =IFERROR(AVERAGE(H10:L10),"N/A") -> 7 | T10: =IFERROR(AVERAGE(M10:Q10),"N/A") -> 6.8 | U10: =IF(ISNUMBER(S10),(R10*0.3333+S10*0.3333+T10*0.3334),"N/A") -> 6.53336 | V10: =IF(NOT(ISNUMBER(U10)),"NO ACTION",IF(U10>=7,"BUY",IF(U10>=4,"HOLD","SELL"))) -> HOLD | W10: 2026-09-06
A11: TSLA | B11: Tesla Inc | C11: 5 | D11: 6 | E11: 6 | F11: 3 | G11: 3 | H11: 0 | I11: 9 | J11: 1 | K11: 2 | L11: 10 | M11: 7 | N11: 5 | O11: 6 | P11: 7 | Q11: 3 | R11: =IFERROR(AVERAGE(C11:G11),"N/A") -> 4.6 | S11: =IFERROR(AVERAGE(H11:L11),"N/A") -> 4.4 | T11: =IFERROR(AVERAGE(M11:Q11),"N/A") -> 5.6 | U11: =IF(ISNUMBER(S11),(R11*0.3333+S11*0.3333+T11*0.3334),"N/A") -> 4.86674 | V11: =IF(NOT(ISNUMBER(U11)),"NO ACTION",IF(U11>=7,"BUY",IF(U11>=4,"HOLD","SELL"))) -> HOLD | W11: 2026-09-06
